struqture_qutip_interface/__init__.py
struqture_qutip_interface/qutip_interface.py
struqture_qutip_interface-0.4.0.dist-info/licenses/LICENSE
struqture_qutip_interface-0.4.0.dist-info/METADATA
struqture_qutip_interface-0.4.0.dist-info/WHEEL
struqture_qutip_interface-0.4.0.dist-info/top_level.txt
struqture_qutip_interface-0.4.0.dist-info/RECORD
