Metadata-Version: 2.4
Name: struqture_qutip_interface
Version: 0.4.0
Author-email: HQS Quantum Simulation GmbH <info@quantumsimulations.de>
Maintainer-email: Matteo Lodi <matteo.lodi@quantumsimulations.de>
License:                                  Apache License
Requires-Python: >=3.9
License-File: LICENSE
Requires-Dist: qutip<6,>=5
Requires-Dist: struqture_py>=2.0
Requires-Dist: numpy
Provides-Extra: tests
Requires-Dist: pytest-cov; extra == "tests"
Requires-Dist: pytest; extra == "tests"
Provides-Extra: dev
Requires-Dist: ruff; extra == "dev"
Requires-Dist: darglint; extra == "dev"
Requires-Dist: bandit; extra == "dev"
Requires-Dist: mypy; extra == "dev"
Requires-Dist: black; extra == "dev"
Provides-Extra: docs
Requires-Dist: sphinx>=2.1; extra == "docs"
Requires-Dist: nbsphinx; extra == "docs"
Requires-Dist: pygments; extra == "docs"
Requires-Dist: recommonmark; extra == "docs"
Requires-Dist: myst_parser; extra == "docs"
Requires-Dist: sphinx_rtd_theme; extra == "docs"
Requires-Dist: tomli; extra == "docs"
Dynamic: license-file
